envinfopy/__init__.py
envinfopy/__main__.py
envinfopy/__version__.py
envinfopy/_const.py
envinfopy/py.typed
envinfopy-0.2.0.dist-info/LICENSE
envinfopy-0.2.0.dist-info/METADATA
envinfopy-0.2.0.dist-info/WHEEL
envinfopy-0.2.0.dist-info/top_level.txt
envinfopy-0.2.0.dist-info/RECORD
