Metadata-Version: 2.1
Name: envinfopy
Version: 0.2.0
Summary: envinfopy is a Python Library to get execution environment information.
Home-page: https://github.com/thombashi/envinfopy
Author: Tsuyoshi Hombashi
Author-email: tsuyoshi.hombashi@gmail.com
License: MIT License
Project-URL: Source, https://github.com/thombashi/envinfopy
Project-URL: Tracker, https://github.com/thombashi/envinfopy/issues
Keywords: environment,uname,version,markdown
Classifier: Development Status :: 4 - Beta
Classifier: Environment :: Console
Classifier: Intended Audience :: Developers
Classifier: Intended Audience :: Information Technology
Classifier: License :: OSI Approved :: MIT License
Classifier: Operating System :: OS Independent
Classifier: Programming Language :: Python :: 3
Classifier: Programming Language :: Python :: 3.7
Classifier: Programming Language :: Python :: 3.8
Classifier: Programming Language :: Python :: 3.9
Classifier: Programming Language :: Python :: 3.10
Classifier: Programming Language :: Python :: 3.11
Classifier: Programming Language :: Python :: 3 :: Only
Classifier: Programming Language :: Python :: Implementation :: CPython
Classifier: Programming Language :: Python :: Implementation :: PyPy
Classifier: Topic :: Software Development :: Libraries
Classifier: Topic :: Software Development :: Libraries :: Python Modules
Classifier: Topic :: Terminals
Requires-Python: >=3.7
Provides-Extra: all
Provides-Extra: cli
Provides-Extra: dev
Provides-Extra: distro
Provides-Extra: markdown
Provides-Extra: test
License-File: LICENSE
